{
  "meta": {
    "host": "ep-dry-sunset-ampa3wrs-pooler.c-5.us-east-1.aws.neon.tech",
    "which": "active",
    "cutoff": "2026-05-30T00:00:00.000Z",
    "takenAt": "2026-06-15T00:03:15.139Z",
    "needIds": [
      "d4ed39a7-54be-4c04-8904-773aa7a8a0b2",
      "0dbd45ad-b940-40df-b6b8-e39a56ee74cb",
      "df26bf21-d91b-4c18-9b0f-ab0a80b09dbe",
      "3d0876fe-8647-4144-819b-4d11d22daecb",
      "b12b2982-e4cb-4e0f-b5c3-903ab598482e",
      "59e55100-c35c-419d-a8f6-718b24b398a2",
      "efad0149-ad8d-457e-b4df-9a9ec9c59d03"
    ],
    "missionIds": [
      "a321e3e1-da86-40ca-8353-9891b9707615",
      "449953f1-ff5b-4e0f-a960-e6141bd27584",
      "f9154459-51a4-49fd-aae9-a5e03a9aec35",
      "13ee3740-bc18-4286-8e14-9916be0e8e39",
      "2af993ef-71f9-4d1c-8220-e31e6a8c54a0",
      "33914a8f-6b21-476f-b88b-7926c5c550b2",
      "12037710-e36d-458b-aedf-4269cc0a8cba",
      "7b05849b-8419-4278-a21b-b897ac8d89ec",
      "5901ead6-bab4-4f70-832b-2364bbcd5b0a",
      "0a34fe09-eda4-4363-a44a-3a56af272f08",
      "170b7754-52f9-4dd1-9562-56eaefef5a40",
      "e0fec304-b560-44ab-bc6f-f7c7857b7068",
      "08fdebb5-c08e-4ec4-82f8-82b674b218fd",
      "a988da81-3812-49a9-b679-b19f9cfc951d",
      "ec92f95e-5a82-4a65-9015-51acf253c9c3"
    ]
  },
  "needs": [
    {
      "id": "d4ed39a7-54be-4c04-8904-773aa7a8a0b2",
      "clientId": "1975a896-d2c5-4e00-92b5-72f590b5f1f8",
      "categoryId": "f53abe28-c851-4d47-a7d9-c3900af11d61",
      "subCategoryId": null,
      "title": "Installation de prises électriques",
      "description": "Besoin d'installer 5 prises électriques dans le salon et la chambre",
      "urgency": "NORMAL",
      "status": "COMPLETED",
      "address": "12 Rue de la Liberté, Bonamoussadi",
      "neighborhood": "Bonamoussadi",
      "city": "Douala",
      "latitude": 4.071490634463832,
      "longitude": 9.737890367442915,
      "preferredDate": "2026-04-25T09:40:23.951Z",
      "preferredTimeSlot": null,
      "flexibleSchedule": true,
      "budgetMin": "50000",
      "budgetMax": "80000",
      "images": "[\"https://images.unsplash.com/photo-1558618666-fcd25c85f82e?w=600\",\"https://images.unsplash.com/photo-1621905252507-b35492cc74b4?w=600\"]",
      "videoUrl": null,
      "depositPaymentId": null,
      "publishedAt": "2026-04-20T09:40:23.951Z",
      "completedAt": "2026-05-02T09:40:23.951Z",
      "createdAt": "2026-05-05T09:40:23.954Z",
      "updatedAt": "2026-05-05T09:40:23.954Z",
      "needImages": [],
      "candidatures": [
        {
          "id": "9d7d6006-ee46-4191-a369-5565c12a9aaa",
          "needId": "d4ed39a7-54be-4c04-8904-773aa7a8a0b2",
          "technicianId": "97b5e8f7-2f84-4a80-8263-4d469c909724",
          "message": "Je suis électricien qualifié avec 8 ans d'expérience. Je peux réaliser votre installation dans les règles de l'art.",
          "proposedDate": "2026-04-25T09:40:26.717Z",
          "proposedPrice": "65000",
          "status": "ACCEPTED",
          "createdAt": "2026-05-05T09:40:26.719Z",
          "updatedAt": "2026-05-05T09:40:26.719Z"
        }
      ],
      "quotations": [
        {
          "id": "b13c6f86-16b5-4210-a5f2-dc89b8296a9c",
          "needId": "d4ed39a7-54be-4c04-8904-773aa7a8a0b2",
          "technicianId": "97b5e8f7-2f84-4a80-8263-4d469c909724",
          "stateOfWork": "État des lieux: Salon et chambre nécessitent 5 prises électriques. Tableau électrique existant en bon état. Câbles à tirer sous gaine.",
          "urgencyLevel": "NORMAL",
          "proposedSolution": "Installation de 5 prises encastrées avec terre, conformes à la norme NF C 15-100. Fourniture et pose de câbles 2,5mm² sous gaine. Protection par disjoncteur 20A.",
          "materials": "[{\"name\":\"Prises encastrées avec terre\",\"quantity\":5,\"unitPrice\":3000},{\"name\":\"Câble 2,5mm² (mètres)\",\"quantity\":25,\"unitPrice\":500},{\"name\":\"Gaine ICTA\",\"quantity\":20,\"unitPrice\":300},{\"name\":\"Disjoncteur 20A\",\"quantity\":1,\"unitPrice\":8000}]",
          "laborCost": "35000",
          "materialsCost": "29000",
          "totalCost": "64000",
          "currency": "XAF",
          "status": "ACCEPTED",
          "validUntil": "2026-06-04T09:40:32.660Z",
          "clientResponse": null,
          "respondedAt": "2026-04-27T09:40:32.660Z",
          "heldPaymentId": null,
          "heldAmount": null,
          "clientSignature": "data:image/png;base64,iVBORw0KGgoAAAANSUhEUgAAAAEAAAABCAYAAAAfFcSJAAAADUlEQVR42mNk+M9QDwADhgGAWjR9awAAAABJRU5ErkJggg==",
          "clientSignedAt": "2026-04-27T09:40:32.660Z",
          "signatureToken": null,
          "signatureTokenExpiresAt": null,
          "missionId": null,
          "createdAt": "2026-05-05T09:40:32.662Z",
          "updatedAt": "2026-05-05T09:40:32.662Z",
          "images": [],
          "counterProposals": []
        }
      ],
      "appointments": [
        {
          "id": "d7b811b6-7751-40cd-b523-c17c588e218e",
          "needId": "d4ed39a7-54be-4c04-8904-773aa7a8a0b2",
          "clientId": "1975a896-d2c5-4e00-92b5-72f590b5f1f8",
          "technicianId": "97b5e8f7-2f84-4a80-8263-4d469c909724",
          "scheduledDate": "2026-04-28T09:40:30.870Z",
          "scheduledTime": "09:00",
          "duration": 180,
          "status": "COMPLETED",
          "address": "12 Rue de la Liberté, Bonamoussadi",
          "latitude": 4.071490634463832,
          "longitude": 9.737890367442915,
          "notes": "Installation de 5 prises électriques",
          "technicianStartedAt": "2026-04-28T07:40:30.870Z",
          "technicianArrivedAt": "2026-04-28T08:10:30.870Z",
          "completedAt": "2026-04-28T12:40:30.870Z",
          "cancelledAt": null,
          "cancellationReason": null,
          "technicianCurrentLat": null,
          "technicianCurrentLng": null,
          "technicianCurrentUpdatedAt": null,
          "createdAt": "2026-05-05T09:40:30.872Z",
          "updatedAt": "2026-05-05T09:40:30.872Z"
        }
      ],
      "payments": [],
      "proximityBroadcast": null
    },
    {
      "id": "0dbd45ad-b940-40df-b6b8-e39a56ee74cb",
      "clientId": "a0e668b0-3a57-4932-901a-806c3309781f",
      "categoryId": "c4bd6eac-428b-4833-8e89-7b3c606c9f66",
      "subCategoryId": null,
      "title": "Réparation fuite d'eau",
      "description": "Fuite au niveau du robinet de la cuisine, urgent",
      "urgency": "URGENT",
      "status": "IN_PROGRESS",
      "address": "45 Boulevard de la République, Akwa",
      "neighborhood": "Akwa",
      "city": "Douala",
      "latitude": 4.051102235165228,
      "longitude": 9.703719931086344,
      "preferredDate": "2026-05-06T09:40:24.671Z",
      "preferredTimeSlot": null,
      "flexibleSchedule": false,
      "budgetMin": "30000",
      "budgetMax": "50000",
      "images": "[\"https://images.unsplash.com/photo-1585704032915-c3400ca199e7?w=600\",\"https://images.unsplash.com/photo-1504328345606-18bbc8c9d7d1?w=600\",\"https://images.unsplash.com/photo-1607472586893-edb57bdc0e39?w=600\"]",
      "videoUrl": null,
      "depositPaymentId": null,
      "publishedAt": "2026-05-03T09:40:24.671Z",
      "completedAt": null,
      "createdAt": "2026-05-05T09:40:24.674Z",
      "updatedAt": "2026-05-05T09:40:24.674Z",
      "needImages": [],
      "candidatures": [
        {
          "id": "e21511fd-0f3c-4e5c-bd08-de923da01df6",
          "needId": "0dbd45ad-b940-40df-b6b8-e39a56ee74cb",
          "technicianId": "c879d95c-3c72-4869-9983-7a3a5c763923",
          "message": "Plombier disponible immédiatement pour intervention urgente.",
          "proposedDate": "2026-05-06T09:40:27.432Z",
          "proposedPrice": "35000",
          "status": "ACCEPTED",
          "createdAt": "2026-05-05T09:40:27.433Z",
          "updatedAt": "2026-05-05T09:40:27.433Z"
        }
      ],
      "quotations": [
        {
          "id": "478d641e-a009-4212-9d0a-95e6b44fbff4",
          "needId": "0dbd45ad-b940-40df-b6b8-e39a56ee74cb",
          "technicianId": "c879d95c-3c72-4869-9983-7a3a5c763923",
          "stateOfWork": "État des lieux: Fuite au niveau du robinet mitigeur de la cuisine. Joint usé. Robinetterie vieillissante.",
          "urgencyLevel": "URGENT",
          "proposedSolution": "Remplacement complet du robinet mitigeur par un modèle moderne avec économie d'eau. Installation avec joints PTFE.",
          "materials": "[{\"name\":\"Robinet mitigeur cuisine\",\"quantity\":1,\"unitPrice\":18000},{\"name\":\"Joints et flexibles\",\"quantity\":1,\"unitPrice\":5000},{\"name\":\"Téflon PTFE\",\"quantity\":1,\"unitPrice\":2000}]",
          "laborCost": "15000",
          "materialsCost": "25000",
          "totalCost": "40000",
          "currency": "XAF",
          "status": "SENT",
          "validUntil": "2026-05-20T09:40:33.474Z",
          "clientResponse": null,
          "respondedAt": null,
          "heldPaymentId": null,
          "heldAmount": null,
          "clientSignature": null,
          "clientSignedAt": null,
          "signatureToken": "abc123-demo-token-plumber",
          "signatureTokenExpiresAt": "2026-05-12T09:40:33.474Z",
          "missionId": null,
          "createdAt": "2026-05-05T09:40:33.476Z",
          "updatedAt": "2026-05-05T09:40:33.476Z",
          "images": [],
          "counterProposals": []
        }
      ],
      "appointments": [
        {
          "id": "84fe1105-2671-40d2-9015-3ba93130ece1",
          "needId": "0dbd45ad-b940-40df-b6b8-e39a56ee74cb",
          "clientId": "a0e668b0-3a57-4932-901a-806c3309781f",
          "technicianId": "c879d95c-3c72-4869-9983-7a3a5c763923",
          "scheduledDate": "2026-05-06T09:40:31.476Z",
          "scheduledTime": "14:00",
          "duration": 120,
          "status": "CONFIRMED",
          "address": "45 Boulevard de la République, Akwa",
          "latitude": 4.051102235165228,
          "longitude": 9.703719931086344,
          "notes": "Réparation fuite robinet cuisine - urgent",
          "technicianStartedAt": null,
          "technicianArrivedAt": null,
          "completedAt": null,
          "cancelledAt": null,
          "cancellationReason": null,
          "technicianCurrentLat": null,
          "technicianCurrentLng": null,
          "technicianCurrentUpdatedAt": null,
          "createdAt": "2026-05-05T09:40:31.478Z",
          "updatedAt": "2026-05-05T09:40:31.478Z"
        }
      ],
      "payments": [],
      "proximityBroadcast": null
    },
    {
      "id": "df26bf21-d91b-4c18-9b0f-ab0a80b09dbe",
      "clientId": "e30651bf-6215-4676-8393-417c5890eaf2",
      "categoryId": "6c3f08f8-ade4-4fb5-b049-6a324e68d8a7",
      "subCategoryId": null,
      "title": "Peinture chambre",
      "description": "Peinture complète d'une chambre (12m²), blanc cassé",
      "urgency": "NORMAL",
      "status": "OPEN",
      "address": "8 Quartier Bonaberi",
      "neighborhood": "Bonabéri",
      "city": "Douala",
      "latitude": 4.072833047519008,
      "longitude": 9.681552190359787,
      "preferredDate": "2026-05-12T09:40:25.816Z",
      "preferredTimeSlot": null,
      "flexibleSchedule": true,
      "budgetMin": "60000",
      "budgetMax": "100000",
      "images": "[\"https://images.unsplash.com/photo-1562259949-e8e7689d7828?w=600\",\"https://images.unsplash.com/photo-1589939705384-5185137a7f0f?w=600\"]",
      "videoUrl": null,
      "depositPaymentId": null,
      "publishedAt": "2026-05-05T09:40:25.816Z",
      "completedAt": null,
      "createdAt": "2026-05-05T09:40:25.818Z",
      "updatedAt": "2026-05-05T09:40:25.818Z",
      "needImages": [],
      "candidatures": [
        {
          "id": "42fd0363-06ca-48ba-b94f-224f85be48b0",
          "needId": "df26bf21-d91b-4c18-9b0f-ab0a80b09dbe",
          "technicianId": "c5f768a3-e643-47df-a7fe-5cc368c8afa1",
          "message": "Peintre professionnel, devis détaillé sur demande. Travail soigné garanti.",
          "proposedDate": "2026-05-12T09:40:27.739Z",
          "proposedPrice": "75000",
          "status": "PENDING",
          "createdAt": "2026-05-05T09:40:27.742Z",
          "updatedAt": "2026-05-05T09:40:27.742Z"
        }
      ],
      "quotations": [],
      "appointments": [],
      "payments": [],
      "proximityBroadcast": null
    },
    {
      "id": "3d0876fe-8647-4144-819b-4d11d22daecb",
      "clientId": "a4594e9e-89b7-4c43-b950-7bc530e803e0",
      "categoryId": "c227f76c-a6d6-48a9-8a4b-a47c34070fc8",
      "subCategoryId": null,
      "title": "Fabrication porte en bois",
      "description": "Besoin d'une porte en bois massif sur mesure",
      "urgency": "NORMAL",
      "status": "COMPLETED",
      "address": "23 Rue Joss, Deido",
      "neighborhood": "Deido",
      "city": "Douala",
      "latitude": 4.051593532290991,
      "longitude": 9.71149788317757,
      "preferredDate": "2026-04-15T09:40:26.070Z",
      "preferredTimeSlot": null,
      "flexibleSchedule": true,
      "budgetMin": "150000",
      "budgetMax": "200000",
      "images": "[\"https://images.unsplash.com/photo-1534237886190-ced735ca4b73?w=600\"]",
      "videoUrl": null,
      "depositPaymentId": null,
      "publishedAt": "2026-04-10T09:40:26.070Z",
      "completedAt": "2026-04-30T09:40:26.070Z",
      "createdAt": "2026-05-05T09:40:26.072Z",
      "updatedAt": "2026-05-05T09:40:26.072Z",
      "needImages": [],
      "candidatures": [
        {
          "id": "0407ba8f-957f-4498-8218-f72bbbbe7892",
          "needId": "3d0876fe-8647-4144-819b-4d11d22daecb",
          "technicianId": "682572c8-2551-4643-b20d-a8ca0895ceac",
          "message": "Menuisier expérimenté, fabrication sur mesure en bois massif. Photos de réalisations disponibles.",
          "proposedDate": "2026-04-15T09:40:29.172Z",
          "proposedPrice": "180000",
          "status": "ACCEPTED",
          "createdAt": "2026-05-05T09:40:29.174Z",
          "updatedAt": "2026-05-05T09:40:29.174Z"
        }
      ],
      "quotations": [
        {
          "id": "fb2ecbb8-4d1f-4b0d-9523-562704c54348",
          "needId": "3d0876fe-8647-4144-819b-4d11d22daecb",
          "technicianId": "682572c8-2551-4643-b20d-a8ca0895ceac",
          "stateOfWork": "État des lieux: Prise de mesures effectuée (H: 210cm x L: 90cm). Porte à réaliser en bois massif (sapelli) avec finition vernis.",
          "urgencyLevel": "NORMAL",
          "proposedSolution": "Fabrication sur mesure d'une porte pleine en bois sapelli. Pose avec paumelles laiton. Finition vernis mat 3 couches.",
          "materials": "[{\"name\":\"Bois sapelli (m²)\",\"quantity\":2.5,\"unitPrice\":35000},{\"name\":\"Paumelles laiton\",\"quantity\":3,\"unitPrice\":8000},{\"name\":\"Serrure encastrée\",\"quantity\":1,\"unitPrice\":15000},{\"name\":\"Vernis mat (litre)\",\"quantity\":2,\"unitPrice\":12000}]",
          "laborCost": "80000",
          "materialsCost": "135500",
          "totalCost": "215500",
          "currency": "XAF",
          "status": "ACCEPTED",
          "validUntil": "2026-06-04T09:40:34.293Z",
          "clientResponse": null,
          "respondedAt": "2026-04-17T09:40:34.293Z",
          "heldPaymentId": null,
          "heldAmount": null,
          "clientSignature": "data:image/png;base64,iVBORw0KGgoAAAANSUhEUgAAAAEAAAABCAYAAAAfFcSJAAAADUlEQVR42mNk+M9QDwADhgGAWjR9awAAAABJRU5ErkJggg==",
          "clientSignedAt": "2026-04-17T09:40:34.293Z",
          "signatureToken": null,
          "signatureTokenExpiresAt": null,
          "missionId": null,
          "createdAt": "2026-05-05T09:40:34.295Z",
          "updatedAt": "2026-05-05T09:40:34.295Z",
          "images": [],
          "counterProposals": []
        }
      ],
      "appointments": [
        {
          "id": "3ee3a51b-02ba-4af3-a3dc-c100af68e3f8",
          "needId": "3d0876fe-8647-4144-819b-4d11d22daecb",
          "clientId": "a4594e9e-89b7-4c43-b950-7bc530e803e0",
          "technicianId": "682572c8-2551-4643-b20d-a8ca0895ceac",
          "scheduledDate": "2026-04-20T09:40:32.245Z",
          "scheduledTime": "10:00",
          "duration": 240,
          "status": "COMPLETED",
          "address": "23 Rue Joss, Deido",
          "latitude": 4.051593532290991,
          "longitude": 9.71149788317757,
          "notes": "Prise de mesures et fabrication porte",
          "technicianStartedAt": "2026-04-20T08:40:32.245Z",
          "technicianArrivedAt": "2026-04-20T09:10:32.245Z",
          "completedAt": "2026-04-20T13:40:32.245Z",
          "cancelledAt": null,
          "cancellationReason": null,
          "technicianCurrentLat": null,
          "technicianCurrentLng": null,
          "technicianCurrentUpdatedAt": null,
          "createdAt": "2026-05-05T09:40:32.247Z",
          "updatedAt": "2026-05-05T09:40:32.247Z"
        }
      ],
      "payments": [],
      "proximityBroadcast": null
    },
    {
      "id": "b12b2982-e4cb-4e0f-b5c3-903ab598482e",
      "clientId": "96c6671a-bd2d-444a-a417-cfff481c33a4",
      "categoryId": "68135aae-94a9-48fb-968e-a2fe52576917",
      "subCategoryId": null,
      "title": "Installation climatiseur",
      "description": "Installation d'un climatiseur split 12000 BTU dans le salon",
      "urgency": "HIGH",
      "status": "IN_PROGRESS",
      "address": "67 Avenue Douala Manga Bell, Bonapriso",
      "neighborhood": "Bonapriso",
      "city": "Douala",
      "latitude": 4.015455864502212,
      "longitude": 9.690442741927958,
      "preferredDate": "2026-05-08T09:40:26.412Z",
      "preferredTimeSlot": null,
      "flexibleSchedule": false,
      "budgetMin": "200000",
      "budgetMax": "300000",
      "images": "[\"https://images.unsplash.com/photo-1585771724684-38269d6639fd?w=600\",\"https://images.unsplash.com/photo-1631545806609-3180c0671163?w=600\"]",
      "videoUrl": null,
      "depositPaymentId": null,
      "publishedAt": "2026-05-05T09:40:26.412Z",
      "completedAt": null,
      "createdAt": "2026-05-05T09:40:26.414Z",
      "updatedAt": "2026-05-05T09:43:43.352Z",
      "needImages": [],
      "candidatures": [
        {
          "id": "bb658a6e-a3ca-436e-9630-1c0ef3754e47",
          "needId": "b12b2982-e4cb-4e0f-b5c3-903ab598482e",
          "technicianId": "97b5e8f7-2f84-4a80-8263-4d469c909724",
          "message": "Ok",
          "proposedDate": "2026-05-08T12:43:00.000Z",
          "proposedPrice": "250000",
          "status": "ACCEPTED",
          "createdAt": "2026-05-05T09:43:40.531Z",
          "updatedAt": "2026-05-05T09:43:43.166Z"
        }
      ],
      "quotations": [],
      "appointments": [],
      "payments": [],
      "proximityBroadcast": null
    },
    {
      "id": "59e55100-c35c-419d-a8f6-718b24b398a2",
      "clientId": "dcc700e8-831b-46de-8c1f-edf4f9d7190d",
      "categoryId": "68135aae-94a9-48fb-968e-a2fe52576917",
      "subCategoryId": null,
      "title": "Clim qui coule",
      "description": "J'ai Hisense de la chambre qui coule ",
      "urgency": "HIGH",
      "status": "OPEN",
      "address": "Douala, Cameroun",
      "neighborhood": "Non spécifié",
      "city": "Douala",
      "latitude": 4.0080007,
      "longitude": 9.710497199999999,
      "preferredDate": null,
      "preferredTimeSlot": "morning",
      "flexibleSchedule": true,
      "budgetMin": "5000",
      "budgetMax": "10000",
      "images": null,
      "videoUrl": null,
      "depositPaymentId": null,
      "publishedAt": null,
      "completedAt": null,
      "createdAt": "2026-05-20T16:26:14.733Z",
      "updatedAt": "2026-05-20T16:26:14.733Z",
      "needImages": [],
      "candidatures": [],
      "quotations": [],
      "appointments": [],
      "payments": [],
      "proximityBroadcast": {
        "id": "8c991b8e-451f-4c5c-91be-2d400257f866",
        "needId": "59e55100-c35c-419d-a8f6-718b24b398a2",
        "currentRadius": 30,
        "maxRadius": 30,
        "expandEvery": 20,
        "lastExpandedAt": "2026-05-20T19:10:01.003Z",
        "isActive": false,
        "notifiedTechnicianIds": "[\"e6e8afae-5bc0-4d18-a41e-a08c743255f3\",\"682572c8-2551-4643-b20d-a8ca0895ceac\",\"cc25b40f-3469-4a23-bf45-db27d01a95cc\",\"c879d95c-3c72-4869-9983-7a3a5c763923\",\"97b5e8f7-2f84-4a80-8263-4d469c909724\",\"ca4f83f3-750e-4e47-8edd-c41277aba812\",\"7e7d85e4-8061-4f24-ad03-367c2d354318\",\"ad3da457-6a72-4d6d-948d-5acf0d31bdeb\",\"3260bb77-4c93-4438-9476-29a0d83c2a96\",\"14fe0629-b93b-4d8b-b24a-df1fa22b7ad5\",\"fbcdede5-235b-41f1-8451-4a04106974fd\",\"7fbd3789-cbe7-4a14-abe3-2dabb65432e9\",\"9e837f61-840a-44f9-9a23-ad5bc7a50fb0\",\"d48a27aa-8b68-4ffe-a61c-f65ac84038a2\",\"bab69aef-9285-4ea7-8f3a-ca6c5fe87866\",\"afa121be-a108-4534-8b74-30d124283e3d\",\"b00693cf-5abb-481b-a16e-bbdcb3ccf8cc\",\"dfbe6ad1-4eb4-4fb5-8d4a-ddd7f019f7a1\",\"01a736f8-c892-470e-bc91-70cfbe3c7f21\",\"5e0432f3-8080-422e-be7a-798588eff062\",\"8434ce55-d23e-456b-b946-d5077951d07f\",\"1aa1a5eb-455b-4c18-a305-df9166868329\",\"6ac65c30-c9b3-48b4-b0d8-a1a07562afe6\",\"2c603615-0277-4a40-8359-aafc0a965b7e\",\"931eee20-4b87-4a3b-a13a-cb822cef6e12\",\"35a06e78-8a0d-412c-8b69-df0ff5d41370\",\"07397297-ccb6-42a5-86e6-6384746025c3\",\"74b54a7b-6a4f-4c6b-a4ee-cc62b18bd42f\"]",
        "createdAt": "2026-05-20T16:26:15.912Z",
        "updatedAt": "2026-05-20T19:30:01.706Z"
      }
    },
    {
      "id": "efad0149-ad8d-457e-b4df-9a9ec9c59d03",
      "clientId": "5c4112c5-be8b-433c-9e1c-20a6864e4b04",
      "categoryId": "c4bd6eac-428b-4833-8e89-7b3c606c9f66",
      "subCategoryId": null,
      "title": "Fuite d'eau à réparer",
      "description": "J'ai une fuite d'eau qui coule en continu et je n'arrive pas à la stopper. Merci de venir diagnostiquer la source de la fuite et la réparer rapidement.",
      "urgency": "URGENT",
      "status": "IN_PROGRESS",
      "address": "Makepe, Douala V, Région du Littoral, Cameroun",
      "neighborhood": null,
      "city": null,
      "latitude": 4.0638116,
      "longitude": 9.7409587,
      "preferredDate": "2026-05-31T00:00:00.000Z",
      "preferredTimeSlot": "morning",
      "flexibleSchedule": true,
      "budgetMin": "500",
      "budgetMax": "2000",
      "images": null,
      "videoUrl": null,
      "depositPaymentId": null,
      "publishedAt": null,
      "completedAt": null,
      "createdAt": "2026-05-29T22:33:34.769Z",
      "updatedAt": "2026-05-29T23:34:12.873Z",
      "needImages": [],
      "candidatures": [
        {
          "id": "37ed71e1-529d-4834-8eee-b13814ab023a",
          "needId": "efad0149-ad8d-457e-b4df-9a9ec9c59d03",
          "technicianId": "9b0dfbda-8d63-492a-a18f-cd53536547c8",
          "message": "Ok telle me",
          "proposedDate": null,
          "proposedPrice": null,
          "status": "ACCEPTED",
          "createdAt": "2026-05-29T22:58:03.161Z",
          "updatedAt": "2026-05-29T23:34:13.430Z"
        }
      ],
      "quotations": [],
      "appointments": [],
      "payments": [],
      "proximityBroadcast": {
        "id": "3e0573c6-0543-4af7-9129-4c4efbf5260b",
        "needId": "efad0149-ad8d-457e-b4df-9a9ec9c59d03",
        "currentRadius": 5,
        "maxRadius": 30,
        "expandEvery": 20,
        "lastExpandedAt": "2026-05-29T23:15:00.620Z",
        "isActive": false,
        "notifiedTechnicianIds": "[\"cc25b40f-3469-4a23-bf45-db27d01a95cc\",\"e6e8afae-5bc0-4d18-a41e-a08c743255f3\",\"c879d95c-3c72-4869-9983-7a3a5c763923\",\"97b5e8f7-2f84-4a80-8263-4d469c909724\",\"ca4f83f3-750e-4e47-8edd-c41277aba812\",\"7e7d85e4-8061-4f24-ad03-367c2d354318\",\"ad3da457-6a72-4d6d-948d-5acf0d31bdeb\",\"3260bb77-4c93-4438-9476-29a0d83c2a96\",\"14fe0629-b93b-4d8b-b24a-df1fa22b7ad5\",\"fbcdede5-235b-41f1-8451-4a04106974fd\",\"7fbd3789-cbe7-4a14-abe3-2dabb65432e9\",\"9e837f61-840a-44f9-9a23-ad5bc7a50fb0\",\"d48a27aa-8b68-4ffe-a61c-f65ac84038a2\",\"bab69aef-9285-4ea7-8f3a-ca6c5fe87866\",\"afa121be-a108-4534-8b74-30d124283e3d\",\"b00693cf-5abb-481b-a16e-bbdcb3ccf8cc\",\"dfbe6ad1-4eb4-4fb5-8d4a-ddd7f019f7a1\",\"01a736f8-c892-470e-bc91-70cfbe3c7f21\",\"5e0432f3-8080-422e-be7a-798588eff062\",\"8434ce55-d23e-456b-b946-d5077951d07f\",\"682572c8-2551-4643-b20d-a8ca0895ceac\",\"9b0dfbda-8d63-492a-a18f-cd53536547c8\"]",
        "createdAt": "2026-05-29T22:33:38.245Z",
        "updatedAt": "2026-05-29T23:35:01.668Z"
      }
    }
  ],
  "missions": [
    {
      "id": "a321e3e1-da86-40ca-8353-9891b9707615",
      "needId": null,
      "quotationId": null,
      "appointmentId": null,
      "clientId": "97977259-cfc9-47a1-8fff-f4a90044f19a",
      "technicianId": "97b5e8f7-2f84-4a80-8263-4d469c909724",
      "status": "IN_PROGRESS",
      "scheduledDate": "2026-03-12T00:00:00.000Z",
      "scheduledTime": "09:00",
      "startedAt": "2026-03-04T10:20:00.683Z",
      "completedAt": null,
      "cancelledAt": null,
      "cancellationReason": null,
      "technicianValidatedAt": null,
      "clientValidatedAt": null,
      "technicianNotes": null,
      "clientNotes": null,
      "address": "Douala",
      "latitude": null,
      "longitude": null,
      "proposedAmount": null,
      "heldPaymentId": null,
      "heldAmount": null,
      "clientPaidAt": null,
      "createdAt": "2026-03-04T10:20:00.686Z",
      "updatedAt": "2026-03-04T10:20:00.686Z",
      "documents": [],
      "ratings": [],
      "conversation": {
        "id": "b8e9cbaf-ca79-435e-88cd-37b217d9a2c3",
        "participantIds": "[\"97977259-cfc9-47a1-8fff-f4a90044f19a\",\"97b5e8f7-2f84-4a80-8263-4d469c909724\"]",
        "missionId": "a321e3e1-da86-40ca-8353-9891b9707615",
        "lastMessageAt": "2026-03-15T23:07:21.725Z",
        "createdAt": "2026-03-04T10:20:03.420Z",
        "updatedAt": "2026-03-15T23:07:21.731Z",
        "messages": [
          {
            "id": "f01865b8-ad24-4bf7-84b5-8a83c017c6a4",
            "conversationId": "b8e9cbaf-ca79-435e-88cd-37b217d9a2c3",
            "senderId": "97977259-cfc9-47a1-8fff-f4a90044f19a",
            "receiverId": "97b5e8f7-2f84-4a80-8263-4d469c909724",
            "content": "yo",
            "messageType": "text",
            "imageUrl": null,
            "fileUrl": null,
            "fileName": null,
            "fileSize": null,
            "duration": null,
            "isRead": false,
            "readAt": null,
            "createdAt": "2026-03-15T23:07:21.731Z"
          }
        ]
      },
      "additionalQuotations": []
    },
    {
      "id": "449953f1-ff5b-4e0f-a960-e6141bd27584",
      "needId": null,
      "quotationId": null,
      "appointmentId": null,
      "clientId": "1975a896-d2c5-4e00-92b5-72f590b5f1f8",
      "technicianId": "97b5e8f7-2f84-4a80-8263-4d469c909724",
      "status": "IN_PROGRESS",
      "scheduledDate": "2026-03-12T00:00:00.000Z",
      "scheduledTime": "11:00",
      "startedAt": "2026-03-04T10:42:15.906Z",
      "completedAt": null,
      "cancelledAt": null,
      "cancellationReason": null,
      "technicianValidatedAt": null,
      "clientValidatedAt": null,
      "technicianNotes": null,
      "clientNotes": null,
      "address": "12 Rue de la Liberté",
      "latitude": 4.0511,
      "longitude": 9.7679,
      "proposedAmount": null,
      "heldPaymentId": null,
      "heldAmount": null,
      "clientPaidAt": null,
      "createdAt": "2026-03-04T10:42:15.907Z",
      "updatedAt": "2026-03-04T10:42:15.907Z",
      "documents": [],
      "ratings": [],
      "conversation": null,
      "additionalQuotations": []
    },
    {
      "id": "f9154459-51a4-49fd-aae9-a5e03a9aec35",
      "needId": null,
      "quotationId": null,
      "appointmentId": null,
      "clientId": "1975a896-d2c5-4e00-92b5-72f590b5f1f8",
      "technicianId": "97b5e8f7-2f84-4a80-8263-4d469c909724",
      "status": "IN_PROGRESS",
      "scheduledDate": "2026-03-06T00:00:00.000Z",
      "scheduledTime": "09:00",
      "startedAt": "2026-03-04T11:24:15.332Z",
      "completedAt": null,
      "cancelledAt": null,
      "cancellationReason": null,
      "technicianValidatedAt": null,
      "clientValidatedAt": null,
      "technicianNotes": null,
      "clientNotes": null,
      "address": "35 Ave des Cocotiers, Douala, Cameroun",
      "latitude": 4.0134386,
      "longitude": 9.717007299999999,
      "proposedAmount": null,
      "heldPaymentId": null,
      "heldAmount": null,
      "clientPaidAt": null,
      "createdAt": "2026-03-04T11:24:15.334Z",
      "updatedAt": "2026-03-04T11:24:15.334Z",
      "documents": [],
      "ratings": [],
      "conversation": null,
      "additionalQuotations": []
    },
    {
      "id": "13ee3740-bc18-4286-8e14-9916be0e8e39",
      "needId": null,
      "quotationId": null,
      "appointmentId": null,
      "clientId": "1975a896-d2c5-4e00-92b5-72f590b5f1f8",
      "technicianId": "97b5e8f7-2f84-4a80-8263-4d469c909724",
      "status": "COMPLETED",
      "scheduledDate": null,
      "scheduledTime": null,
      "startedAt": "2026-03-04T13:19:21.123Z",
      "completedAt": "2026-03-04T13:27:05.090Z",
      "cancelledAt": null,
      "cancellationReason": null,
      "technicianValidatedAt": "2026-03-04T13:26:48.042Z",
      "clientValidatedAt": "2026-03-04T13:27:05.090Z",
      "technicianNotes": null,
      "clientNotes": null,
      "address": "3PGW+7RH makepe st Tropez, 3655, Douala, Cameroun",
      "latitude": 4.0756859,
      "longitude": 9.7471021,
      "proposedAmount": null,
      "heldPaymentId": null,
      "heldAmount": null,
      "clientPaidAt": null,
      "createdAt": "2026-03-04T13:19:21.127Z",
      "updatedAt": "2026-03-04T13:27:05.327Z",
      "documents": [],
      "ratings": [],
      "conversation": null,
      "additionalQuotations": []
    },
    {
      "id": "2af993ef-71f9-4d1c-8220-e31e6a8c54a0",
      "needId": null,
      "quotationId": null,
      "appointmentId": null,
      "clientId": "1975a896-d2c5-4e00-92b5-72f590b5f1f8",
      "technicianId": "97b5e8f7-2f84-4a80-8263-4d469c909724",
      "status": "PENDING",
      "scheduledDate": "2026-03-19T00:00:00.000Z",
      "scheduledTime": "10:25",
      "startedAt": null,
      "completedAt": null,
      "cancelledAt": null,
      "cancellationReason": null,
      "technicianValidatedAt": null,
      "clientValidatedAt": null,
      "technicianNotes": null,
      "clientNotes": null,
      "address": "Douala, Cameroun",
      "latitude": 4.0510564,
      "longitude": 9.7678687,
      "proposedAmount": null,
      "heldPaymentId": null,
      "heldAmount": null,
      "clientPaidAt": null,
      "createdAt": "2026-03-11T12:24:21.745Z",
      "updatedAt": "2026-03-11T12:24:21.745Z",
      "documents": [],
      "ratings": [],
      "conversation": {
        "id": "c25969c4-4f50-490a-8cd3-f33a8ab0a98c",
        "participantIds": "[\"1975a896-d2c5-4e00-92b5-72f590b5f1f8\",\"97b5e8f7-2f84-4a80-8263-4d469c909724\"]",
        "missionId": "2af993ef-71f9-4d1c-8220-e31e6a8c54a0",
        "lastMessageAt": "2026-03-04T13:28:19.850Z",
        "createdAt": "2026-03-04T10:42:18.389Z",
        "updatedAt": "2026-03-11T12:24:26.182Z",
        "messages": [
          {
            "id": "1d61298a-2362-43b2-9741-e40247eba9f0",
            "conversationId": "c25969c4-4f50-490a-8cd3-f33a8ab0a98c",
            "senderId": "1975a896-d2c5-4e00-92b5-72f590b5f1f8",
            "receiverId": "97b5e8f7-2f84-4a80-8263-4d469c909724",
            "content": "yo bro",
            "messageType": "text",
            "imageUrl": null,
            "fileUrl": null,
            "fileName": null,
            "fileSize": null,
            "duration": null,
            "isRead": false,
            "readAt": null,
            "createdAt": "2026-03-04T11:41:22.533Z"
          },
          {
            "id": "aedf83d3-1c44-4516-b752-0bbf66ba550c",
            "conversationId": "c25969c4-4f50-490a-8cd3-f33a8ab0a98c",
            "senderId": "1975a896-d2c5-4e00-92b5-72f590b5f1f8",
            "receiverId": "97b5e8f7-2f84-4a80-8263-4d469c909724",
            "content": "How are you",
            "messageType": "text",
            "imageUrl": null,
            "fileUrl": null,
            "fileName": null,
            "fileSize": null,
            "duration": null,
            "isRead": false,
            "readAt": null,
            "createdAt": "2026-03-04T13:27:38.093Z"
          },
          {
            "id": "56a6c3b1-81d5-409a-aba8-e474e89c7424",
            "conversationId": "c25969c4-4f50-490a-8cd3-f33a8ab0a98c",
            "senderId": "97b5e8f7-2f84-4a80-8263-4d469c909724",
            "receiverId": "1975a896-d2c5-4e00-92b5-72f590b5f1f8",
            "content": "Yes i am good",
            "messageType": "text",
            "imageUrl": null,
            "fileUrl": null,
            "fileName": null,
            "fileSize": null,
            "duration": null,
            "isRead": true,
            "readAt": "2026-03-10T16:15:03.044Z",
            "createdAt": "2026-03-04T13:28:19.852Z"
          }
        ]
      },
      "additionalQuotations": []
    },
    {
      "id": "33914a8f-6b21-476f-b88b-7926c5c550b2",
      "needId": "b12b2982-e4cb-4e0f-b5c3-903ab598482e",
      "quotationId": null,
      "appointmentId": null,
      "clientId": "96c6671a-bd2d-444a-a417-cfff481c33a4",
      "technicianId": "97b5e8f7-2f84-4a80-8263-4d469c909724",
      "status": "SCHEDULED",
      "scheduledDate": "2026-05-08T12:43:00.000Z",
      "scheduledTime": "00:00",
      "startedAt": null,
      "completedAt": null,
      "cancelledAt": null,
      "cancellationReason": null,
      "technicianValidatedAt": null,
      "clientValidatedAt": null,
      "technicianNotes": null,
      "clientNotes": null,
      "address": "67 Avenue Douala Manga Bell, Bonapriso",
      "latitude": 4.015455864502212,
      "longitude": 9.690442741927958,
      "proposedAmount": "250000",
      "heldPaymentId": null,
      "heldAmount": null,
      "clientPaidAt": null,
      "createdAt": "2026-05-05T09:43:44.184Z",
      "updatedAt": "2026-05-05T09:45:03.687Z",
      "documents": [],
      "ratings": [],
      "conversation": {
        "id": "b56d0fef-c27b-43e8-9425-f3635493146f",
        "participantIds": "[\"96c6671a-bd2d-444a-a417-cfff481c33a4\",\"97b5e8f7-2f84-4a80-8263-4d469c909724\"]",
        "missionId": "33914a8f-6b21-476f-b88b-7926c5c550b2",
        "lastMessageAt": null,
        "createdAt": "2026-05-05T09:43:45.925Z",
        "updatedAt": "2026-05-05T09:43:45.925Z",
        "messages": []
      },
      "additionalQuotations": []
    },
    {
      "id": "12037710-e36d-458b-aedf-4269cc0a8cba",
      "needId": null,
      "quotationId": null,
      "appointmentId": null,
      "clientId": "67db4fb8-dc2a-4ffd-bc68-2f828a0a9d31",
      "technicianId": "10d74b11-1c9a-41c1-9829-0b84da1ce89b",
      "status": "PENDING_VALIDATION",
      "scheduledDate": "2026-03-25T00:00:00.000Z",
      "scheduledTime": "09:00",
      "startedAt": "2026-04-08T17:08:29.996Z",
      "completedAt": null,
      "cancelledAt": null,
      "cancellationReason": null,
      "technicianValidatedAt": "2026-04-12T11:35:46.780Z",
      "clientValidatedAt": null,
      "technicianNotes": null,
      "clientNotes": null,
      "address": "Makepe Missoke, Douala, Cameroun",
      "latitude": 4.0605537,
      "longitude": 9.7382479,
      "proposedAmount": null,
      "heldPaymentId": null,
      "heldAmount": null,
      "clientPaidAt": null,
      "createdAt": "2026-04-08T17:03:09.174Z",
      "updatedAt": "2026-04-12T11:35:46.785Z",
      "documents": [],
      "ratings": [],
      "conversation": null,
      "additionalQuotations": []
    },
    {
      "id": "7b05849b-8419-4278-a21b-b897ac8d89ec",
      "needId": null,
      "quotationId": null,
      "appointmentId": null,
      "clientId": "67db4fb8-dc2a-4ffd-bc68-2f828a0a9d31",
      "technicianId": "10d74b11-1c9a-41c1-9829-0b84da1ce89b",
      "status": "COMPLETED",
      "scheduledDate": null,
      "scheduledTime": null,
      "startedAt": null,
      "completedAt": "2026-04-13T08:59:08.072Z",
      "cancelledAt": null,
      "cancellationReason": null,
      "technicianValidatedAt": null,
      "clientValidatedAt": null,
      "technicianNotes": null,
      "clientNotes": null,
      "address": "Makepe Missoke, Douala, Cameroun",
      "latitude": 4.0605537,
      "longitude": 9.7382479,
      "proposedAmount": null,
      "heldPaymentId": null,
      "heldAmount": null,
      "clientPaidAt": null,
      "createdAt": "2026-04-12T01:00:26.283Z",
      "updatedAt": "2026-04-13T08:59:08.080Z",
      "documents": [],
      "ratings": [],
      "conversation": null,
      "additionalQuotations": []
    },
    {
      "id": "5901ead6-bab4-4f70-832b-2364bbcd5b0a",
      "needId": null,
      "quotationId": null,
      "appointmentId": null,
      "clientId": "67db4fb8-dc2a-4ffd-bc68-2f828a0a9d31",
      "technicianId": "10d74b11-1c9a-41c1-9829-0b84da1ce89b",
      "status": "PENDING",
      "scheduledDate": "2026-04-13T16:25:00.000Z",
      "scheduledTime": "00:00",
      "startedAt": null,
      "completedAt": null,
      "cancelledAt": null,
      "cancellationReason": null,
      "technicianValidatedAt": null,
      "clientValidatedAt": null,
      "technicianNotes": null,
      "clientNotes": null,
      "address": "85 rue Dominique Savio Primaire Bp: 5485, Douala, Cameroun",
      "latitude": 4.0252875,
      "longitude": 9.6942199,
      "proposedAmount": null,
      "heldPaymentId": null,
      "heldAmount": null,
      "clientPaidAt": null,
      "createdAt": "2026-04-13T12:35:01.424Z",
      "updatedAt": "2026-04-13T12:35:01.424Z",
      "documents": [],
      "ratings": [],
      "conversation": {
        "id": "d4b59f01-00ce-4d55-b27b-a34d826060a4",
        "participantIds": "[\"67db4fb8-dc2a-4ffd-bc68-2f828a0a9d31\",\"10d74b11-1c9a-41c1-9829-0b84da1ce89b\"]",
        "missionId": "5901ead6-bab4-4f70-832b-2364bbcd5b0a",
        "lastMessageAt": "2026-04-08T17:04:59.452Z",
        "createdAt": "2026-04-08T17:03:14.516Z",
        "updatedAt": "2026-04-13T12:35:06.676Z",
        "messages": [
          {
            "id": "1b4cab4d-32f7-4aac-b0fb-d691abf69509",
            "conversationId": "d4b59f01-00ce-4d55-b27b-a34d826060a4",
            "senderId": "67db4fb8-dc2a-4ffd-bc68-2f828a0a9d31",
            "receiverId": "10d74b11-1c9a-41c1-9829-0b84da1ce89b",
            "content": "Check",
            "messageType": "text",
            "imageUrl": null,
            "fileUrl": null,
            "fileName": null,
            "fileSize": null,
            "duration": null,
            "isRead": true,
            "readAt": "2026-04-12T00:34:15.461Z",
            "createdAt": "2026-04-08T17:04:59.453Z"
          }
        ]
      },
      "additionalQuotations": []
    },
    {
      "id": "0a34fe09-eda4-4363-a44a-3a56af272f08",
      "needId": null,
      "quotationId": null,
      "appointmentId": null,
      "clientId": "67db4fb8-dc2a-4ffd-bc68-2f828a0a9d31",
      "technicianId": "9b0dfbda-8d63-492a-a18f-cd53536547c8",
      "status": "PENDING_VALIDATION",
      "scheduledDate": "2026-04-14T11:40:00.000Z",
      "scheduledTime": "00:00",
      "startedAt": "2026-04-14T11:22:13.523Z",
      "completedAt": null,
      "cancelledAt": null,
      "cancellationReason": null,
      "technicianValidatedAt": "2026-04-14T13:21:13.818Z",
      "clientValidatedAt": null,
      "technicianNotes": null,
      "clientNotes": null,
      "address": "Makepe Missoke, Douala, Cameroun",
      "latitude": 4.0605537,
      "longitude": 9.7382479,
      "proposedAmount": "25000",
      "heldPaymentId": "6a5309ff-66ce-4a5d-aea6-11e5f1d37455",
      "heldAmount": "25000",
      "clientPaidAt": "2026-04-14T10:51:03.179Z",
      "createdAt": "2026-04-14T09:42:42.223Z",
      "updatedAt": "2026-04-14T13:21:13.836Z",
      "documents": [],
      "ratings": [],
      "conversation": null,
      "additionalQuotations": []
    },
    {
      "id": "170b7754-52f9-4dd1-9562-56eaefef5a40",
      "needId": null,
      "quotationId": null,
      "appointmentId": null,
      "clientId": "67db4fb8-dc2a-4ffd-bc68-2f828a0a9d31",
      "technicianId": "9b0dfbda-8d63-492a-a18f-cd53536547c8",
      "status": "COMPLETED",
      "scheduledDate": null,
      "scheduledTime": null,
      "startedAt": null,
      "completedAt": "2026-04-14T13:59:43.593Z",
      "cancelledAt": null,
      "cancellationReason": null,
      "technicianValidatedAt": "2026-04-14T13:59:43.593Z",
      "clientValidatedAt": "2026-04-14T13:59:43.593Z",
      "technicianNotes": null,
      "clientNotes": null,
      "address": "Makepe Missoke, Douala, Cameroun",
      "latitude": 4.0605537,
      "longitude": 9.7382479,
      "proposedAmount": null,
      "heldPaymentId": null,
      "heldAmount": null,
      "clientPaidAt": null,
      "createdAt": "2026-04-14T11:53:10.854Z",
      "updatedAt": "2026-04-14T13:59:43.602Z",
      "documents": [],
      "ratings": [],
      "conversation": {
        "id": "b3b32f43-eab6-4723-a4ea-66c5e390f81b",
        "participantIds": "[\"67db4fb8-dc2a-4ffd-bc68-2f828a0a9d31\",\"9b0dfbda-8d63-492a-a18f-cd53536547c8\"]",
        "missionId": "170b7754-52f9-4dd1-9562-56eaefef5a40",
        "lastMessageAt": "2026-04-14T13:27:12.142Z",
        "createdAt": "2026-04-14T09:42:48.836Z",
        "updatedAt": "2026-04-14T13:27:12.145Z",
        "messages": [
          {
            "id": "db572ac5-168c-4670-9b9b-7594b034b6ce",
            "conversationId": "b3b32f43-eab6-4723-a4ea-66c5e390f81b",
            "senderId": "67db4fb8-dc2a-4ffd-bc68-2f828a0a9d31",
            "receiverId": "9b0dfbda-8d63-492a-a18f-cd53536547c8",
            "content": "Hello",
            "messageType": "text",
            "imageUrl": null,
            "fileUrl": null,
            "fileName": null,
            "fileSize": null,
            "duration": null,
            "isRead": true,
            "readAt": "2026-04-14T13:26:33.963Z",
            "createdAt": "2026-04-14T13:26:25.243Z"
          },
          {
            "id": "89bf86a7-880e-435b-be16-ed29a173f3cf",
            "conversationId": "b3b32f43-eab6-4723-a4ea-66c5e390f81b",
            "senderId": "9b0dfbda-8d63-492a-a18f-cd53536547c8",
            "receiverId": "67db4fb8-dc2a-4ffd-bc68-2f828a0a9d31",
            "content": "Hi",
            "messageType": "text",
            "imageUrl": null,
            "fileUrl": null,
            "fileName": null,
            "fileSize": null,
            "duration": null,
            "isRead": true,
            "readAt": "2026-04-14T13:26:57.235Z",
            "createdAt": "2026-04-14T13:26:40.266Z"
          },
          {
            "id": "de82d2aa-ab94-4aa9-b387-9a28f4fe04dc",
            "conversationId": "b3b32f43-eab6-4723-a4ea-66c5e390f81b",
            "senderId": "67db4fb8-dc2a-4ffd-bc68-2f828a0a9d31",
            "receiverId": "9b0dfbda-8d63-492a-a18f-cd53536547c8",
            "content": "How are you doing?",
            "messageType": "text",
            "imageUrl": null,
            "fileUrl": null,
            "fileName": null,
            "fileSize": null,
            "duration": null,
            "isRead": true,
            "readAt": "2026-04-14T13:28:17.078Z",
            "createdAt": "2026-04-14T13:27:12.145Z"
          }
        ]
      },
      "additionalQuotations": []
    },
    {
      "id": "e0fec304-b560-44ab-bc6f-f7c7857b7068",
      "needId": null,
      "quotationId": null,
      "appointmentId": null,
      "clientId": "c03de53d-1213-41bb-9ef1-7ced694b4f25",
      "technicianId": "99f16cba-9416-4ddc-8647-d3e6cd5b411e",
      "status": "SCHEDULED",
      "scheduledDate": "2026-04-15T16:33:00.000Z",
      "scheduledTime": "00:00",
      "startedAt": null,
      "completedAt": null,
      "cancelledAt": null,
      "cancellationReason": null,
      "technicianValidatedAt": null,
      "clientValidatedAt": null,
      "technicianNotes": null,
      "clientNotes": null,
      "address": "Makepe Missoke, Douala, Cameroun",
      "latitude": 4.0605537,
      "longitude": 9.7382479,
      "proposedAmount": "25000",
      "heldPaymentId": null,
      "heldAmount": null,
      "clientPaidAt": null,
      "createdAt": "2026-04-14T14:34:07.653Z",
      "updatedAt": "2026-04-14T14:40:38.016Z",
      "documents": [],
      "ratings": [],
      "conversation": {
        "id": "7d4c014a-a7e2-48d8-a00c-349a4bce4901",
        "participantIds": "[\"c03de53d-1213-41bb-9ef1-7ced694b4f25\",\"99f16cba-9416-4ddc-8647-d3e6cd5b411e\"]",
        "missionId": "e0fec304-b560-44ab-bc6f-f7c7857b7068",
        "lastMessageAt": null,
        "createdAt": "2026-04-14T14:34:09.440Z",
        "updatedAt": "2026-04-14T14:34:09.440Z",
        "messages": []
      },
      "additionalQuotations": []
    },
    {
      "id": "08fdebb5-c08e-4ec4-82f8-82b674b218fd",
      "needId": null,
      "quotationId": null,
      "appointmentId": null,
      "clientId": "064740f7-681b-40d1-9b12-00874cdd7d6b",
      "technicianId": "094273bb-e6bb-4e60-ba75-6f9b2c1b8842",
      "status": "PENDING_VALIDATION",
      "scheduledDate": "2026-04-16T09:30:00.000Z",
      "scheduledTime": "00:00",
      "startedAt": "2026-04-15T12:45:13.399Z",
      "completedAt": null,
      "cancelledAt": null,
      "cancellationReason": null,
      "technicianValidatedAt": "2026-04-15T12:54:13.628Z",
      "clientValidatedAt": null,
      "technicianNotes": null,
      "clientNotes": null,
      "address": "Makepe Missoke, Douala, Cameroun",
      "latitude": 4.0605537,
      "longitude": 9.7382479,
      "proposedAmount": "150",
      "heldPaymentId": "07594e10-b73d-497a-b11c-270ed9b864fc",
      "heldAmount": "150",
      "clientPaidAt": "2026-04-15T12:44:31.057Z",
      "createdAt": "2026-04-15T12:37:16.726Z",
      "updatedAt": "2026-04-15T12:54:13.629Z",
      "documents": [],
      "ratings": [],
      "conversation": null,
      "additionalQuotations": []
    },
    {
      "id": "a988da81-3812-49a9-b679-b19f9cfc951d",
      "needId": null,
      "quotationId": null,
      "appointmentId": null,
      "clientId": "064740f7-681b-40d1-9b12-00874cdd7d6b",
      "technicianId": "094273bb-e6bb-4e60-ba75-6f9b2c1b8842",
      "status": "COMPLETED",
      "scheduledDate": null,
      "scheduledTime": null,
      "startedAt": null,
      "completedAt": "2026-04-15T12:59:48.634Z",
      "cancelledAt": null,
      "cancellationReason": null,
      "technicianValidatedAt": "2026-04-15T12:59:48.634Z",
      "clientValidatedAt": "2026-04-15T12:59:48.634Z",
      "technicianNotes": null,
      "clientNotes": null,
      "address": "Makepe Missoke, Douala, Cameroun",
      "latitude": 4.0605537,
      "longitude": 9.7382479,
      "proposedAmount": null,
      "heldPaymentId": null,
      "heldAmount": null,
      "clientPaidAt": null,
      "createdAt": "2026-04-15T12:50:15.983Z",
      "updatedAt": "2026-04-15T12:59:48.636Z",
      "documents": [],
      "ratings": [],
      "conversation": {
        "id": "6a249161-025e-44aa-b27d-ceeaa086ab00",
        "participantIds": "[\"064740f7-681b-40d1-9b12-00874cdd7d6b\",\"094273bb-e6bb-4e60-ba75-6f9b2c1b8842\"]",
        "missionId": "a988da81-3812-49a9-b679-b19f9cfc951d",
        "lastMessageAt": null,
        "createdAt": "2026-04-15T12:37:18.511Z",
        "updatedAt": "2026-04-15T12:50:18.024Z",
        "messages": []
      },
      "additionalQuotations": []
    },
    {
      "id": "ec92f95e-5a82-4a65-9015-51acf253c9c3",
      "needId": "efad0149-ad8d-457e-b4df-9a9ec9c59d03",
      "quotationId": null,
      "appointmentId": null,
      "clientId": "5c4112c5-be8b-433c-9e1c-20a6864e4b04",
      "technicianId": "9b0dfbda-8d63-492a-a18f-cd53536547c8",
      "status": "PENDING",
      "scheduledDate": "2026-05-31T00:00:00.000Z",
      "scheduledTime": "03:37",
      "startedAt": null,
      "completedAt": null,
      "cancelledAt": null,
      "cancellationReason": null,
      "technicianValidatedAt": null,
      "clientValidatedAt": null,
      "technicianNotes": null,
      "clientNotes": null,
      "address": "Makepe, Douala V, Région du Littoral, Cameroun",
      "latitude": 4.0638116,
      "longitude": 9.7409587,
      "proposedAmount": null,
      "heldPaymentId": null,
      "heldAmount": null,
      "clientPaidAt": null,
      "createdAt": "2026-05-29T23:34:17.604Z",
      "updatedAt": "2026-05-29T23:34:17.604Z",
      "documents": [],
      "ratings": [],
      "conversation": {
        "id": "56bac60b-a48b-4364-b9f7-10eb5affd569",
        "participantIds": "[\"5c4112c5-be8b-433c-9e1c-20a6864e4b04\",\"9b0dfbda-8d63-492a-a18f-cd53536547c8\"]",
        "missionId": "ec92f95e-5a82-4a65-9015-51acf253c9c3",
        "lastMessageAt": null,
        "createdAt": "2026-05-29T23:34:22.024Z",
        "updatedAt": "2026-05-29T23:34:22.024Z",
        "messages": []
      },
      "additionalQuotations": []
    }
  ]
}